cat_win/__init__.py
cat_win/__main__.py
cat_win/repl.py
cat_win/res/signatures.json
cat_win/src/__init__.py
cat_win/src/argparser.py
cat_win/src/cat.py
cat_win/src/const/__init__.py
cat_win/src/const/argconstants.py
cat_win/src/const/colorconstants.py
cat_win/src/const/defaultconstants.py
cat_win/src/const/escapecodes.py
cat_win/src/const/regex.py
cat_win/src/domain/arguments.py
cat_win/src/domain/file.py
cat_win/src/domain/files.py
cat_win/src/persistence/__init__.py
cat_win/src/persistence/cconfig.py
cat_win/src/persistence/config.py
cat_win/src/service/__init__.py
cat_win/src/service/cbase64.py
cat_win/src/service/checksum.py
cat_win/src/service/clipboard.py
cat_win/src/service/converter.py
cat_win/src/service/diffviewer.py
cat_win/src/service/editor.py
cat_win/src/service/fileattributes.py
cat_win/src/service/formatter.py
cat_win/src/service/hexeditor.py
cat_win/src/service/more.py
cat_win/src/service/rawviewer.py
cat_win/src/service/stringfinder.py
cat_win/src/service/strings.py
cat_win/src/service/summary.py
cat_win/src/service/visualizer.py
cat_win/src/service/helper/__init__.py
cat_win/src/service/helper/archiveviewer.py
cat_win/src/service/helper/diffviewerhelper.py
cat_win/src/service/helper/editorhelper.py
cat_win/src/service/helper/editorsearchhelper.py
cat_win/src/service/helper/environment.py
cat_win/src/service/helper/iohelper.py
cat_win/src/service/helper/levenshtein.py
cat_win/src/service/helper/progressbar.py
cat_win/src/service/helper/tmpfilehelper.py
cat_win/src/service/helper/utility.py
cat_win/src/service/helper/utilityold.py
cat_win/src/service/helper/vishelper.py
cat_win/src/service/helper/winstreams.py
cat_win/src/web/__init__.py
cat_win/src/web/updatechecker.py
cat_win/src/web/urls.py
cat_win/tests/__init__.py
cat_win/tests/mocks/__init__.py
cat_win/tests/mocks/edit.py
cat_win/tests/mocks/error.py
cat_win/tests/mocks/pbar.py
cat_win/tests/mocks/std.py
cat_win/tests/resources/test.bin
cat_win/tests/resources/test.tar.gz
cat_win-1.10.4.dist-info/entry_points.txt
cat_win-1.10.4.dist-info/licenses/LICENSE
cat_win-1.10.4.dist-info/WHEEL
cat_win-1.10.4.dist-info/METADATA
cat_win-1.10.4.dist-info/RECORD
