Metadata-Version: 2.4
Name: cat_win
Version: 1.10.4
Summary: Simple Text-Processing and -Analytics Command Line Tool made in Python.
Keywords: cat,analytics,texteditor,hexeditor,command-line-tool,textprocessing
Author: Silas A. Kraume
Author-email: silas.kraume1552@gmail.com
Requires-Python: >=3.6
Classifier: License :: OSI Approved :: MIT License
Classifier: Programming Language :: Python
Classifier: Programming Language :: Python :: 3
Classifier: Programming Language :: Python :: 3.6
Classifier: Programming Language :: Python :: 3.7
Classifier: Programming Language :: Python :: 3.8
Classifier: Programming Language :: Python :: 3.9
Classifier: Programming Language :: Python :: 3.10
Classifier: Programming Language :: Python :: 3.11
Classifier: Programming Language :: Python :: 3.12
Classifier: Programming Language :: Python :: 3.13
Classifier: Programming Language :: Python :: Implementation :: CPython
Classifier: Programming Language :: Python :: Implementation :: PyPy
Classifier: Environment :: Console
Classifier: Environment :: Console :: Curses
Classifier: Operating System :: OS Independent
Classifier: Topic :: Terminals
Classifier: Topic :: Text Editors
Classifier: Topic :: Text Editors :: Text Processing
Classifier: Topic :: Text Processing
License-File: LICENSE
Requires-Dist: windows-curses!=2.3.1; platform_system=='Windows' and platform_python_implementation!='PyPy'
Requires-Dist: colorama~=0.4.0 ; extra == "cfix" and ( platform_system=='Windows')
Requires-Dist: pyperclip~=1.8.0 ; extra == "clip"
Project-URL: Changelog, https://github.com/SilenZcience/cat_win/blob/main/CHANGELOG.md#changelog
Project-URL: Documentation, https://github.com/SilenZcience/cat_win/blob/main/DOCUMENTATION.md#cat_win
Project-URL: Download, https://github.com/SilenZcience/cat_win/tarball/master
Project-URL: Github, https://github.com/SilenZcience/cat_win
Project-URL: Homepage, https://github.com/SilenZcience/cat_win
Project-URL: Issues, https://github.com/SilenZcience/cat_win/issues
Provides-Extra: cfix
Provides-Extra: clip
